SB2_SMIT04653/__init__.py
SB2_SMIT04653-0.0.1.dist-info/LICENCE.txt
SB2_SMIT04653-0.0.1.dist-info/METADATA
SB2_SMIT04653-0.0.1.dist-info/WHEEL
SB2_SMIT04653-0.0.1.dist-info/top_level.txt
SB2_SMIT04653-0.0.1.dist-info/RECORD
